tests/__init__.py
tests/test_connect.py
tests/test_tls_connect.py
tests/test_unix_connect.py
tests/test_zone.py
unbound_console/__init__.py
unbound_console/remotecontrol.py
unbound_console-0.6.6.dist-info/licenses/LICENSE
unbound_console-0.6.6.dist-info/METADATA
unbound_console-0.6.6.dist-info/WHEEL
unbound_console-0.6.6.dist-info/top_level.txt
unbound_console-0.6.6.dist-info/RECORD
