Metadata-Version: 2.4
Name: unbound_console
Version: 0.6.6
Summary: Python console for unbound
Home-page: https://github.com/dmachard/unbound-console
Author: Denis MACHARD
Author-email: d.machard@gmail.com
Keywords: unbound console control remote client
Platform: any
Classifier: License :: OSI Approved :: MIT License
Classifier: Programming Language :: Python :: 3
Classifier: Operating System :: OS Independent
Classifier: Topic :: Software Development :: Libraries
License-File: LICENSE
Provides-Extra: yaml
Requires-Dist: pyyaml; extra == "yaml"
Dynamic: author
Dynamic: author-email
Dynamic: classifier
Dynamic: description
Dynamic: description-content-type
Dynamic: home-page
Dynamic: keywords
Dynamic: license-file
Dynamic: platform
Dynamic: provides-extra
Dynamic: summary
